davey-0.1.3.dist-info/METADATA
davey-0.1.3.dist-info/WHEEL
davey/__init__.py
davey/__init__.pyi
davey/davey.cpython-311-x86_64-linux-gnu.so
davey/py.typed
davey-0.1.3.dist-info/RECORD
